secretstuff/__init__.py
secretstuff/api/__init__.py
secretstuff/api/pipeline.py
secretstuff/config/__init__.py
secretstuff/config/dummy_values.py
secretstuff/config/labels.py
secretstuff/core/__init__.py
secretstuff/core/identifier.py
secretstuff/core/redactor.py
secretstuff/core/reverse_mapper.py
secretstuff-1.0.1.dist-info/licenses/LICENSE
tests/__init__.py
tests/test_identifier.py
tests/test_pipeline.py
tests/test_redactor.py
tests/test_reverse_mapper.py
secretstuff-1.0.1.dist-info/METADATA
secretstuff-1.0.1.dist-info/WHEEL
secretstuff-1.0.1.dist-info/top_level.txt
secretstuff-1.0.1.dist-info/RECORD
